SpeechToText/__init__.py
abhay-0.1.dist-info/METADATA
abhay-0.1.dist-info/WHEEL
abhay-0.1.dist-info/top_level.txt
abhay-0.1.dist-info/RECORD
