Metadata-Version: 2.4
Name: Abhay
Version: 0.1
Summary: this is speechToText pakage craeted by OM 
Author: OM
Author-email: abhayvermaav389@gmail.com
Dynamic: author
Dynamic: author-email
Dynamic: summary
